{"subjects": ["franchise:Red Rising", "series:Red Rising Trilogy", "series:Red Rising Saga", "form:novel", "genre:science fiction", "Fantasy", "Fiction", "Dystopia", "Young Adult", "Resistance to Government", "Amerikanisches Englisch", "Social classes", "Adventure"], "key": "/works/OL17076473W", "title": "Red Rising", "authors": [{"author": {"key": "/authors/OL7621609A"}, "type": {"key": "/type/author_role"}}], "type": {"key": "/type/work"}, "covers": [7316188, 14212161, 14212162, 14212163, 13672534, 12224196, 8185003, 8407136, 8775095, 13839661, 15179172], "subject_times": ["The Future"], "subject_people": ["Darrow", "Sevro", "Mustang", "Victra"], "description": "\"I live for the dream that my children will be born free,\" she says. \"That they will be what they like. That they will own the land their father gave them.\"\r\n\r\n\"I live for you,\" I say sadly.\r\n\r\nEo kisses my cheek. \"Then you must live for more.\"\r\n\r\nDarrow is a Red, a member of the lowest caste in the color-coded society of the future. Like his fellow Reds, he works all day, believing that he and his people are making the surface of Mars livable for future generations.\r\n\r\nYet he spends his life willingly, knowing that his blood and sweat will one day result in a better world for his children.\r\n\r\nBut Darrow and his kind have been betrayed. Soon he discovers that humanity already reached the surface generations ago. Vast cities and sprawling parks spread across the planet. Darrow\u2014and Reds like him\u2014are nothing more than slaves to a decadent ruling class.\r\n\r\nInspired by a longing for justice, and driven by the memory of lost love, Darrow sacrifices everything to infiltrate the legendary Institute, a proving ground for the dominant Gold caste, where the next generation of humanity's overlords struggle for power. He will be forced to compete for his life and the very future of civilization against the best and most brutal of Society's ruling class. There, he will stop at nothing to bring down his enemies... even if it means he has to become one of them to do so.", "links": [{"title": "New York Time \u201cWhat to Read\u201d", "url": "https://https://www.nytimes.com/2018/01/26/books/review/pierce-brown-red-rising-best-seller.html", "type": {"key": "/type/link"}}, {"title": "Turning Page Review", "url": "https://www.turningpagemag.com/2017/05/a-review-of-red-rising-trilogy-by.html?m=1#.YxNPnyUpAWM", "type": {"key": "/type/link"}}], "subject_places": ["Solar system", "Moon", "Jupiter", "Mars"], "identifiers": {"bookbrainz": ["a52bd9c4-7b9a-48e4-8f2b-8122d882265f"], "musicbrainz": ["5281c5d0-46f7-4ba2-807a-9b0891ce7920"], "librarything": ["13865214"], "wikidata": ["Q18393778"], "isfdb": ["1664916", "1868251", "3090379", "1986204", "2090537", "2793057", "2789859"], "goodreads": ["21580644"]}, "series": [{"series": {"key": "/series/OL327572L"}, "position": "1"}], "latest_revision": 19, "revision": 19, "created": {"type": "/type/datetime", "value": "2014-12-05T08:58:48.807004"}, "last_modified": {"type": "/type/datetime", "value": "2026-03-13T07:20:08.633061"}}